screenshot/__init__.py
screenshot/__main__.py
screenshot/clint.py
screenshot/screenshot.py
screenshot_server-0.1.3.dist-info/METADATA
screenshot_server-0.1.3.dist-info/WHEEL
screenshot_server-0.1.3.dist-info/entry_points.txt
screenshot_server-0.1.3.dist-info/top_level.txt
screenshot_server-0.1.3.dist-info/RECORD
