Metadata-Version: 2.4
Name: screenshot-server
Version: 0.1.3
Summary: Add your description here
Requires-Python: >=3.10
Requires-Dist: mcp[cli]>=1.4.1
Requires-Dist: pillow>=11.1.0
Requires-Dist: pyautogui>=0.9.54
Requires-Dist: pyscreeze>=1.0.1
